LICENSE
MANIFEST.in
README.rst
buildout.cfg
develop.cfg
pyproject.toml
requirements.txt
setup.py
version.txt
bob/__init__.py
bob.learn.libsvm.egg-info/PKG-INFO
bob.learn.libsvm.egg-info/SOURCES.txt
bob.learn.libsvm.egg-info/dependency_links.txt
bob.learn.libsvm.egg-info/entry_points.txt
bob.learn.libsvm.egg-info/not-zip-safe
bob.learn.libsvm.egg-info/requires.txt
bob.learn.libsvm.egg-info/top_level.txt
bob/learn/__init__.py
bob/learn/libsvm/__init__.py
bob/learn/libsvm/file.cpp
bob/learn/libsvm/machine.cpp
bob/learn/libsvm/main.cpp
bob/learn/libsvm/test_machine.py
bob/learn/libsvm/test_trainer.py
bob/learn/libsvm/trainer.cpp
bob/learn/libsvm/utils.cpp
bob/learn/libsvm/version.cpp
bob/learn/libsvm/cpp/file.cpp
bob/learn/libsvm/cpp/machine.cpp
bob/learn/libsvm/cpp/trainer.cpp
bob/learn/libsvm/data/heart.out
bob/learn/libsvm/data/heart.svmdata
bob/learn/libsvm/data/heart.svmmodel
bob/learn/libsvm/data/heart_no_probs.svmmodel
bob/learn/libsvm/data/heart_one_class.svmmodel
bob/learn/libsvm/data/iris.out
bob/learn/libsvm/data/iris.svmdata
bob/learn/libsvm/data/iris.svmmodel
bob/learn/libsvm/include/bob.learn.libsvm/api.h
bob/learn/libsvm/include/bob.learn.libsvm/config.h
bob/learn/libsvm/include/bob.learn.libsvm/file.h
bob/learn/libsvm/include/bob.learn.libsvm/machine.h
bob/learn/libsvm/include/bob.learn.libsvm/trainer.h
doc/c_cpp_api.rst
doc/conf.py
doc/doxygen.rc
doc/guide.rst
doc/index.rst
doc/links.rst
doc/py_api.rst